objectwalker/__init__.py
objectwalker/__main__.py
objectwalker/core.py
objectwalker/filters/EmptyFilter.py
objectwalker/filters/__init__.py
objectwalker/filters/by_object/__init__.py
objectwalker/filters/by_object/name/FilterObjectNameContains.py
objectwalker/filters/by_object/name/FilterObjectNameEndsWith.py
objectwalker/filters/by_object/name/FilterObjectNameEquals.py
objectwalker/filters/by_object/name/FilterObjectNameIsPythonBuiltin.py
objectwalker/filters/by_object/name/FilterObjectNameStartsWith.py
objectwalker/filters/by_object/name/__init__.py
objectwalker/filters/by_object/value/FilterObjectValueContains.py
objectwalker/filters/by_object/value/FilterObjectValueEndsWith.py
objectwalker/filters/by_object/value/FilterObjectValueEquals.py
objectwalker/filters/by_object/value/FilterObjectValueStartsWith.py
objectwalker/filters/by_object/value/__init__.py
objectwalker/filters/by_path/FilterPathContains.py
objectwalker/filters/by_path/FilterPathEndsWith.py
objectwalker/filters/by_path/FilterPathStartsWith.py
objectwalker/filters/by_path/__init__.py
objectwalker/filters/by_type/FilterTypeIsBuiltinFunctionOrMethod.py
objectwalker/filters/by_type/FilterTypeIsMethodWrapper.py
objectwalker/filters/by_type/FilterTypeIsModule.py
objectwalker/filters/by_type/__init__.py
objectwalker/tests/Test_RegExMatcher.py
objectwalker/tests/Test_Search.py
objectwalker/tests/__init__.py
objectwalker/tests/start_tests.py
objectwalker/utils/RegExMatcher.py
objectwalker/utils/Reporter.py
objectwalker/utils/__init__.py
objectwalker-2.2.1.dist-info/METADATA
objectwalker-2.2.1.dist-info/WHEEL
objectwalker-2.2.1.dist-info/entry_points.txt
objectwalker-2.2.1.dist-info/top_level.txt
objectwalker-2.2.1.dist-info/RECORD
