Metadata-Version: 2.1
Name: objectwalker
Version: 2.2.1
Home-page: https://github.com/p0dalirius/objectwalker
Author: Podalirius
Author-email: podalirius@protonmail.com
License: GPL2
Classifier: Programming Language :: Python :: 3
Classifier: License :: OSI Approved :: GNU General Public License v2 (GPLv2)
Classifier: Operating System :: OS Independent
Requires-Python: >=3.6
